crucible/__init__.py
crucible/cli.py
crucible/errors.py
crucible/models.py
crucible/server.py
crucible/domain/__init__.py
crucible/domain/detection.py
crucible/enforcement/__init__.py
crucible/enforcement/assertions.py
crucible/enforcement/budget.py
crucible/enforcement/compliance.py
crucible/enforcement/models.py
crucible/enforcement/patterns.py
crucible/enforcement/bundled/error-handling.yaml
crucible/enforcement/bundled/security.yaml
crucible/enforcement/bundled/smart-contract.yaml
crucible/hooks/__init__.py
crucible/hooks/claudecode.py
crucible/hooks/precommit.py
crucible/knowledge/__init__.py
crucible/knowledge/loader.py
crucible/knowledge/principles/API_DESIGN.md
crucible/knowledge/principles/COMMITS.md
crucible/knowledge/principles/DATABASE.md
crucible/knowledge/principles/DOCUMENTATION.md
crucible/knowledge/principles/ERROR_HANDLING.md
crucible/knowledge/principles/FP.md
crucible/knowledge/principles/GITIGNORE.md
crucible/knowledge/principles/OBSERVABILITY.md
crucible/knowledge/principles/PRECOMMIT.md
crucible/knowledge/principles/SECURITY.md
crucible/knowledge/principles/SMART_CONTRACT.md
crucible/knowledge/principles/SYSTEM_DESIGN.md
crucible/knowledge/principles/TESTING.md
crucible/knowledge/principles/TYPE_SAFETY.md
crucible/review/__init__.py
crucible/review/core.py
crucible/skills/__init__.py
crucible/skills/loader.py
crucible/skills/accessibility-engineer/SKILL.md
crucible/skills/backend-engineer/SKILL.md
crucible/skills/customer-success/SKILL.md
crucible/skills/data-engineer/SKILL.md
crucible/skills/devops-engineer/SKILL.md
crucible/skills/fde-engineer/SKILL.md
crucible/skills/formal-verification/SKILL.md
crucible/skills/gas-optimizer/SKILL.md
crucible/skills/incident-responder/SKILL.md
crucible/skills/mev-researcher/SKILL.md
crucible/skills/mobile-engineer/SKILL.md
crucible/skills/performance-engineer/SKILL.md
crucible/skills/product-engineer/SKILL.md
crucible/skills/protocol-architect/SKILL.md
crucible/skills/security-engineer/SKILL.md
crucible_mcp-1.2.0.dist-info/METADATA
crucible_mcp-1.2.0.dist-info/WHEEL
crucible_mcp-1.2.0.dist-info/entry_points.txt
crucible_mcp-1.2.0.dist-info/top_level.txt
crucible_mcp-1.2.0.dist-info/RECORD
