Metadata-Version: 2.4
Name: crucible-mcp
Version: 1.2.0
Summary: Code review MCP server for Claude. Not affiliated with Atlassian.
Author: be.nvy
License-Expression: MIT
Keywords: mcp,code-review,static-analysis,claude
Requires-Python: >=3.11
Requires-Dist: mcp>=1.0.0
Requires-Dist: pyyaml>=6.0
Requires-Dist: anthropic>=0.40.0
Provides-Extra: dev
Requires-Dist: pytest>=8.0; extra == "dev"
Requires-Dist: pytest-asyncio>=0.23; extra == "dev"
Requires-Dist: mypy>=1.8; extra == "dev"
Requires-Dist: ruff>=0.3; extra == "dev"
